tasdos/__init__.py
tasdos/adapter.py
tasdos/extractref.py
tasdos/mapping.py
tasdos/mergevcf.py
tasdos/params.py
tasdos/refindex.py
tasdos/tasdosa.py
tasdos/tasdosb.py
tasdos/tasdosc.py
tasdos/trimmomatic.py
tasdos/utils.py
tasdos-0.0.1.dist-info/LICENSE
tasdos-0.0.1.dist-info/METADATA
tasdos-0.0.1.dist-info/WHEEL
tasdos-0.0.1.dist-info/entry_points.txt
tasdos-0.0.1.dist-info/top_level.txt
tasdos-0.0.1.dist-info/RECORD
